evaluate_supporter/__init__.py
evaluate_supporter/metrics/__init__.py
evaluate_supporter/metrics/average_metrics.py
evaluate_supporter/metrics/custom_accuracy.py
evaluate_supporter/metrics/mean_average_precision.py
evaluate_supporter/metrics/psnr.py
evaluate_supporter-0.0.1.dist-info/METADATA
evaluate_supporter-0.0.1.dist-info/WHEEL
evaluate_supporter-0.0.1.dist-info/top_level.txt
evaluate_supporter-0.0.1.dist-info/RECORD
