Metadata-Version: 2.1
Name: evaluate-supporter
Version: 0.0.1
Summary: Evaluate supporter
Home-page: https://github.com/automatethem/evaluate-supporter
Author: Sang Ki Kwon
Author-email: automatethem@gmail.com
License: MIT
Platform: UNKNOWN
Requires-Dist: evaluate
Requires-Dist: torchmetrics
